{
    "intelligit": "IntelliGit",
    "extension.description": "コミットグラフ、コミット詳細、シェルフワークフロー、ファイル変更エクスプローラーを備えた VS Code 向け IntelliJ スタイルの Git UI。",
    "view.commit": "コミット",
    "view.graph": "グラフ",
    "view.mergeConflicts": "マージの競合",
    "command.showGitLog": "Gitログを表示",
    "command.undock": "ドッキング解除...",
    "command.dockIntelliGit": "ドック IntelliGit",
    "command.refresh": "更新",
    "command.filterByBranch": "ブランチで絞り込む",
    "command.selectRepository": "リポジトリを選択",
    "command.checkout": "チェックアウト",
    "command.newBranchFrom": "新しいブランチを作成...",
    "command.checkoutAndRebaseOntoCurrent": "チェックアウトして現在のブランチにリベース",
    "command.rebaseCurrentOntoSelected": "現在のデータを選択したデータにリベースする",
    "command.mergeIntoCurrent": "現在のシステムに統合",
    "command.update": "アップデート",
    "command.push": "プッシュ",
    "command.rename": "名前を変更する...",
    "command.delete": "消去",
    "command.rollback": "ロールバック",
    "command.jumpToSource": "ソースへジャンプ",
    "command.shelveChanges": "変更をシェルブ",
    "command.showHistory": "履歴を表示",
    "command.compareWithRevision": "改訂版と比較",
    "command.compareWithBranch": "ブランチと比較",
    "command.compareWithLocal": "ローカルと比較",
    "command.cherryPickSelectedChange": "選択した変更をチェリーピック",
    "command.revertSelectedChange": "選択した変更を元に戻す",
    "command.refreshing": "爽快…",
    "command.openMergeConflict": "マージの競合が発生",
    "command.detectJetBrainsMergeTool": "JetBrains Merge Tool を検出",
    "command.openInJetBrainsMergeTool": "JetBrains Merge Toolで開く",
    "command.acceptYours": "現在の変更を採用",
    "command.acceptTheirs": "受信側の変更を採用",
    "command.openConflictSession": "オープンな紛争解決セッション",
    "command.toggleUndockedWindow": "ドッキング解除されたウィンドウの切り替え",
    "command.cloneRepository": "クローンリポジトリ",
    "command.openFolder": "フォルダーを開く",
    "command.initializeRepository": "リポジトリを初期化する",
    "command.publishBranch": "ブランチを公開",
    "configuration.jetbrainsMergeTool.path.markdownDescription": "JetBrains IDE のバイナリ パス/コマンド (`pycharm`、`idea`、`webstorm`)、または macOS の `.app` バンドル パスを指定します。IntelliGit は `.app` バンドルを `Contents/MacOS` 内の実行可能ファイルに自動的に解決します。",
    "configuration.jetbrainsMergeTool.preferExternal.markdownDescription": "マージの競合を開く際は、外部のJetBrainsマージツールを優先的に使用します。JetBrainsへのパスが設定されていない場合、または起動に失敗した場合は、VS Codeの内部マージエディターにフォールバックします。",
    "configuration.tooltips.enabled.markdownDescription": "IntelliGitウィンドウ内のツールチップ（コミットグラフ、ブランチ列など）を有効または無効にします。",
    "configuration.undockableWindow.markdownDescription": "「Gitログを表示」が呼び出されたときにIntelliGitを統合エディタータブとして開き、VS Codeのネイティブなセカンドモニターへのドッキング解除を可能にします。",
    "configuration.icons.enum.color": "IntelliGitのカラーアイコンを使用する（デフォルト）。",
    "configuration.icons.enum.standard": "VS Codeのモノクロアイコンスタイルを使用し、組み込みパネルとの一貫性を保ちます。",
    "configuration.icons.markdownDescription": "IntelliGitコミットパネルのアイコンスタイル。`standard`はVS Codeのモノクロアイコン（デフォルト）を使用し、`color`はIntelliGitのカラーアイコンを使用します。",
    "configuration.commitWindowPosition.enum.auto": "VS Code の `workbench.sideBar.location` 設定（デフォルト）に従います。",
    "configuration.commitWindowPosition.enum.left": "コミットパネルを、ドッキング解除済み／タブ付きウィンドウの左側に配置します。",
    "configuration.commitWindowPosition.enum.right": "コミットパネルを、ドッキング解除済み／タブ付きウィンドウの右側に配置します。",
    "configuration.commitWindowPosition.markdownDescription": "ドッキング解除/タブ付き IntelliGit ウィンドウ内でのコミット パネルの位置。`auto` (デフォルト) は VS Code の `workbench.sideBar.location` に従います。`left` と `right` は左右どちらかに強制的に配置します。",
    "view.fileCountBadge": "変更されたファイル"
}
